git_delta/__init__.py
git_delta-0.0.1.dist-info/LICENSE
git_delta-0.0.1.dist-info/METADATA
git_delta-0.0.1.dist-info/WHEEL
git_delta-0.0.1.dist-info/top_level.txt
git_delta-0.0.1.dist-info/RECORD
