Metadata-Version: 2.1
Name: git-delta
Version: 0.0.1
Summary: A syntax-highlighting pager for git
Author-email: Thomas Otto <th1000s-2020@posteo.net>
Project-URL: Homepage, https://github.com/dandavison/delta
Classifier: License :: OSI Approved :: MIT License
Requires-Python: >=3.3
License-File: LICENSE
